{
  "title": "Vũ Vương",
  "author": "Độc Du",
  "category": "Võ Hiệp",
  "status": "Full",
  "coverImage": "https://gacsach.top/sites/default/files/styles/book310/public/vu-vuong.jpg",
  "description": "Dùng võ nhập đạo, Đạp Hư Lăng Thần, ta chính là Vũ Vương chi Vương!\nMộ Hàn là một đứa con riêng bị bỏ rơi của Mộ gia Liệt Sơn Thành, đột nhiên Tử Hư Thần Cung xuất hiện, vì hắn mở ra thần thông đại đạo kỳ dị. Thần bí ngàn vạn Thiên Vực thế giới từ từ bày ra...\nAi đã từng đọc truyện của Độc Du thì cũng rõ phong cách của tác giả, Vũ Vương cũng phải là ngoại lệ, nhân vật chính đi lên từ thấp rồi dần lên cao, tình tiết nhanh dồn dập, mạch truyện logic không kéo dài lê thê, đặc biệt là tính cách nhân vật chính không chịu cúi đầu, vì thế truyện sẽ tràn ngập PK từ đấu đến cuối.\nĐẳng cấp võ giả: Nhất trọng Ngoại Tráng, nhị trọng Nội Dưỡng, tam trọng Thực Khí, tứ trọng Đại Thông, ngũ trọng Yên Hà, lục trọng Bách Khiếu, thất trọng Ngọc Xu, bát trọng Không Cốc, cửu trọng Vũ Hóa.",
  "rating": "",
  "votes": "",
  "views": "288986",
  "totalChapters": 10,
  "chapters": [
    {
      "title": "Vũ Vương - Phần 01",
      "url": "https://gacsach.top/doc-online/vu-vuong-phan-01",
      "index": 1
    },
    {
      "title": "Vũ Vương - Phần 02",
      "url": "https://gacsach.top/doc-online/vu-vuong-phan-02",
      "index": 2
    },
    {
      "title": "Vũ Vương - Phần 03",
      "url": "https://gacsach.top/doc-online/vu-vuong-phan-03",
      "index": 3
    },
    {
      "title": "Vũ Vương - Phần 04",
      "url": "https://gacsach.top/doc-online/vu-vuong-phan-04",
      "index": 4
    },
    {
      "title": "Vũ Vương - Phần 05",
      "url": "https://gacsach.top/doc-online/vu-vuong-phan-05",
      "index": 5
    },
    {
      "title": "Vũ Vương - Phần 06",
      "url": "https://gacsach.top/doc-online/vu-vuong-phan-06",
      "index": 6
    },
    {
      "title": "Vũ Vương - Phần 07",
      "url": "https://gacsach.top/doc-online/vu-vuong-phan-07",
      "index": 7
    },
    {
      "title": "Vũ Vương - Phần 08",
      "url": "https://gacsach.top/doc-online/vu-vuong-phan-08",
      "index": 8
    },
    {
      "title": "Vũ Vương - Phần 09",
      "url": "https://gacsach.top/doc-online/vu-vuong-phan-09",
      "index": 9
    },
    {
      "title": "Vũ Vương - Phần 10",
      "url": "https://gacsach.top/doc-online/vu-vuong-phan-10",
      "index": 10
    }
  ]
}