{
  "title": "Tứ quái TKKG - Tập 08: Bầy thú trong lâu đài",
  "author": "Stefan Wolf",
  "category": "Văn học phương TâyTrinh thám",
  "status": "Full",
  "coverImage": "https://gacsach.top/sites/default/files/styles/book310/public/tu-quai-tkkg-tap-8-bay-thu-tro.0.jpg",
  "description": "Tác phẩm: Tứ quái TKKG\nTác giả: Stefan Wolf\nTập 8: Bầy thú trong lâu đài\nNguyên bản tiếng Đức: “Auf der Spur der Vogeljager”\nNhà xuất bản Pelikan – Hannover 1980\nDịch giả: Vũ Hương Giang\nPhóng tác: Bùi Chí Vinh\nTủ sách: Truyện trinh thám – Văn học nước ngoài\nNhà xuất bản Kim Đồng, 1994\nKhổ sách: 10,5 x 14,5 cm\nSố trang: 160 trang\nGiá sách: 2.500 đ\nThông tin Ebook\nĐánh máy: Bim_HF và Thovpa\nThực hiện ebook: Zaqqaz\nThực hiện bởi\nnhóm Biên tập viên :\nAriko Yuta – Du Ca – tuongmy\n(Tìm - Chỉnh sửa – Đăng)",
  "rating": "10",
  "votes": "1",
  "views": "12786",
  "totalChapters": 9,
  "chapters": [
    {
      "title": "Tứ quái TKKG (Tập 8) - Chương 01",
      "url": "https://gacsach.top/doc-online/100972/tu-quai-tkkg-tap-8-chuong-01.html",
      "index": 1
    },
    {
      "title": "Tứ quái TKKG (Tập 8) - Chương 02",
      "url": "https://gacsach.top/doc-online/100973/tu-quai-tkkg-tap-8-chuong-02.html",
      "index": 2
    },
    {
      "title": "Tứ quái TKKG (Tập 8) - Chương 03",
      "url": "https://gacsach.top/doc-online/100974/tu-quai-tkkg-tap-8-chuong-03.html",
      "index": 3
    },
    {
      "title": "Tứ quái TKKG (Tập 8) - Chương 04 - 05",
      "url": "https://gacsach.top/doc-online/100975/tu-quai-tkkg-tap-8-chuong-04-05.html",
      "index": 4
    },
    {
      "title": "Tứ quái TKKG (Tập 8) - Chương 06",
      "url": "https://gacsach.top/doc-online/100976/tu-quai-tkkg-tap-8-chuong-06.html",
      "index": 5
    },
    {
      "title": "Tứ quái TKKG (Tập 8) - Chương 07",
      "url": "https://gacsach.top/doc-online/100977/tu-quai-tkkg-tap-8-chuong-07.html",
      "index": 6
    },
    {
      "title": "Tứ quái TKKG (Tập 8) - Chương 08",
      "url": "https://gacsach.top/doc-online/100978/tu-quai-tkkg-tap-8-chuong-08.html",
      "index": 7
    },
    {
      "title": "Tứ quái TKKG (Tập 8) - Chương 09",
      "url": "https://gacsach.top/doc-online/100979/tu-quai-tkkg-tap-8-chuong-09.html",
      "index": 8
    },
    {
      "title": "Tứ quái TKKG (Tập 8) - Chương 10 (Hết)",
      "url": "https://gacsach.top/doc-online/100980/tu-quai-tkkg-tap-8-chuong-10-het.html",
      "index": 9
    }
  ]
}